parsy-stubs/__init__.pyi
parsy-stubs/py.typed
parsy_stubs-2.1.2.dist-info/LICENSE
parsy_stubs-2.1.2.dist-info/METADATA
parsy_stubs-2.1.2.dist-info/WHEEL
parsy_stubs-2.1.2.dist-info/RECORD
