Metadata-Version: 2.1
Name: parsy-stubs
Version: 2.1.2
Summary: 
Author: Basile Dura
Author-email: basile@bdura.me
Requires-Python: >=3.10,<4.0
Classifier: Programming Language :: Python :: 3
Classifier: Programming Language :: Python :: 3.10
Classifier: Programming Language :: Python :: 3.11
Classifier: Programming Language :: Python :: 3.12
